fer/__init__.py
fer/main.py
id_fer-0.4.0.dist-info/LICENSE
id_fer-0.4.0.dist-info/METADATA
id_fer-0.4.0.dist-info/WHEEL
id_fer-0.4.0.dist-info/top_level.txt
id_fer-0.4.0.dist-info/RECORD
