Metadata-Version: 2.1
Name: id-fer
Version: 0.4.0
Summary: Takes an image or video/stream as input and returns detected faces and emotions.
Home-page: https://github.com/IntrospectData/id-fer-capture
Author: Bradley Reimers
Author-email: b.a.reimers@gmail.com
License: MIT
Download-URL: https://github.com/IntrospectData/facial-expression-recognizer/archive/0.4.0.tar.gz
Keywords: facial,detection,expression,emotion,recognition,ai,machine,vision,artificial,intelligence
Platform: UNKNOWN
Classifier: Development Status :: 3 - Alpha
Classifier: Intended Audience :: Developers
Classifier: Topic :: Scientific/Engineering :: Image Recognition
Classifier: License :: OSI Approved :: MIT License
Classifier: Programming Language :: Python :: 3
Classifier: Programming Language :: Python :: 3.7
Requires-Dist: numpy
Requires-Dist: opencv-python
Requires-Dist: python-magic
Requires-Dist: tensorflow
